mbkauthepy/__init__.py
mbkauthepy/config.py
mbkauthepy/db.py
mbkauthepy/middleware.py
mbkauthepy/routes.py
mbkauthepy/utils.py
mbkauthepy/templates/2fa.handlebars
mbkauthepy/templates/Error.handlebars
mbkauthepy/templates/loginmbkauthe.handlebars
mbkauthepy/templates/showmessage.handlebars
mbkauthepy-1.6.8.dist-info/licenses/LICENSE
mbkauthepy-1.6.8.dist-info/METADATA
mbkauthepy-1.6.8.dist-info/WHEEL
mbkauthepy-1.6.8.dist-info/top_level.txt
mbkauthepy-1.6.8.dist-info/RECORD
