Metadata-Version: 2.4
Name: mbkauthepy
Version: 1.6.8
Summary: A fully featured, secure, and extensible authentication system for Python Flask applications. Originally ported from the Node.js version to provide multi-language support for full-stack apps.
Author-email: Maaz Waheed <maaz.waheed@mbktechstudio.com>
License: Mozilla Public License Version 2.0
Project-URL: Homepage, https://github.com/42Wor/mbkauthepy
Project-URL: Repository, https://github.com/42Wor/mbkauthepy
Keywords: flask,authentication,session,auth,postgresql,security
Classifier: Development Status :: 3 - Alpha
Classifier: Intended Audience :: Developers
Classifier: Topic :: Software Development :: Libraries :: Python Modules
Classifier: Topic :: System :: Systems Administration :: Authentication/Directory
Classifier: Topic :: Security
Classifier: Framework :: Flask
Classifier: License :: OSI Approved :: Mozilla Public License 2.0 (MPL 2.0)
Classifier: Programming Language :: Python :: 3
Classifier: Programming Language :: Python :: 3.8
Classifier: Programming Language :: Python :: 3.9
Classifier: Programming Language :: Python :: 3.10
Classifier: Programming Language :: Python :: 3.11
Classifier: Programming Language :: Python :: 3.12
Classifier: Operating System :: OS Independent
Classifier: Environment :: Web Environment
Requires-Python: >=3.8
License-File: LICENSE
Requires-Dist: Flask>=2.0
Requires-Dist: Flask-Session>=0.5
Requires-Dist: psycopg2-binary>=2.9
Requires-Dist: python-dotenv>=1.0
Requires-Dist: bcrypt>=4.0
Requires-Dist: requests>=2.28
Requires-Dist: pyotp>=2.8
Requires-Dist: Flask-Cors>=4.0
Requires-Dist: SQLAlchemy>=1.4
Requires-Dist: importlib-metadata; python_version < "3.10"
Requires-Dist: pybars3>=0.9.7
Dynamic: license-file
